[
  {"max": 100, "min": 95.1, "text": "🔮 이것은 다빈치의 환생인가요? 신의 손을 가지셨군요! Perfect!"},
  {"max": 95, "min": 90.1, "text": "📐 자를 대고 그린 것 아닌가요? 소름 돋는 완벽함입니다!"},
  {"max": 90, "min": 85.1, "text": "⭐ 와우! 인간 컴퍼스 발견! 엄청나게 정교한 원입니다."},
  {"max": 85, "min": 80.1, "text": "🥇 훌륭합니다! 예술적인 감각이 돋보이는 둥근 원이네요."},
  {"max": 80, "min": 75.1, "text": "👍 제법 안정적이고 이쁜 원입니다. 상위권 진입 완료!"},
  {"max": 75, "min": 70.1, "text": "🙂 둥글둥글하니 보기 좋습니다. 조금만 더 다듬어봐요!"},
  {"max": 70, "min": 65.1, "text": "👀 음, 원이라고 부르기에 큰 무리는 없는 형태군요."},
  {"max": 65, "min": 60.1, "text": "🥚 달걀인가요? 한쪽이 살짝 길쭉해진 느낌이 듭니다."},
  {"max": 60, "min": 55.1, "text": "⚾ 찌그러진 야구공 같네요. 손목에 힘을 조금만 빼보세요."},
  {"max": 55, "min": 50.1, "text": "😮 동그라미라기보단... 찐만두에 가까운 형상입니다."},
  {"max": 50, "min": 45.1, "text": "🪨 길가에 굴러다니는 평범한 조약돌을 그리셨군요."},
  {"max": 45, "min": 40.1, "text": "🥐 겉보기엔 둥글지만 자세히 보면 크루아상 같습니다."},
  {"max": 40, "min": 35.1, "text": "⚠️ 조심하세요! 원이 각지기 시작했습니다. 다각형의 기운이...!"},
  {"max": 35, "min": 30.1, "text": "🥔 혹시 감자를 좋아하시나요? 전형적인 못난이 감자 모양!"},
  {"max": 30, "min": 25.1, "text": "🎈 물풍선을 바닥에 툭 떨어뜨렸을 때의 모양이네요."},
  {"max": 25, "min": 20.1, "text": "💨 원을 그리다가 바람에 휙 날아가 버린 듯한 찌그러짐입니다."},
  {"max": 20, "min": 15.1, "text": "❓ 수수께끼의 추상화 발견! 동그라미를 그리려던 게 맞으시죠...?"},
  {"max": 15, "min": 10.1, "text": "💥 쿠당탕탕! 원이 대폭발을 일으켜 형체를 알아볼 수 없습니다."},
  {"max": 10, "min": 5.1, "text": "📉 충격적! 지렁이가 기어간 자국 아닌가요? 정성이 필요합니다."},
  {"max": 5, "min": 0, "text": "😱 아방가르드 그 자체... 원에 대한 모독입니다! 다시 도전하세요!"}
]